README.txt
setup.cfg
setup.py
repoze/__init__.py
repoze.who.plugins.openid.egg-info/PKG-INFO
repoze.who.plugins.openid.egg-info/SOURCES.txt
repoze.who.plugins.openid.egg-info/dependency_links.txt
repoze.who.plugins.openid.egg-info/entry_points.txt
repoze.who.plugins.openid.egg-info/namespace_packages.txt
repoze.who.plugins.openid.egg-info/not-zip-safe
repoze.who.plugins.openid.egg-info/requires.txt
repoze.who.plugins.openid.egg-info/top_level.txt
repoze/who/__init__.py
repoze/who/plugins/__init__.py
repoze/who/plugins/openid/__init__.py
repoze/who/plugins/openid/classifiers.py
repoze/who/plugins/openid/identification.py
repoze/who/plugins/openid/tests/__init__.py
repoze/who/plugins/openid/tests/consumer.py
repoze/who/plugins/openid/tests/test_challenge.py