Metadata-Version: 1.0
Name: repoze.who.plugins.openid
Version: 0.5.1
Summary: An OpenID plugin for repoze.who
Home-page: http://quantumcore.org/docs/repoze.who.plugins.openid
Author: Christian Scholz
Author-email: cs@comlounge.net
License: BSD-derived (http://www.repoze.org/LICENSE.txt)
Keywords: openid repoze who identification authentication plugin
Platform: UNKNOWN
Classifier: Programming Language :: Python
Classifier: Development Status :: 4 - Beta
Classifier: Intended Audience :: Developers
Classifier: Natural Language :: English
Classifier: Operating System :: OS Independent
Classifier: Topic :: Software Development :: Libraries :: Python Modules
Classifier: Topic :: Internet :: WWW/HTTP :: WSGI :: Middleware
